{"device":{"systemVersion":"15.4.1","systemName":"iOS","model":"iPhone","name":"iPhone (2)"},"samples":[{"sample":{"webUsageByCategory":[],"totalScreenWakes":1,"applicationUsageByCategory":["SRDeviceUsageCategoryPhotoAndVideo",[{"textInputSessions":[],"reportApplicationIdentifier":"FCFB2CD2-E55C-41EA-B9E1-C90BD6D17E60","usageTime":501,"bundleIdentifier":"com.apple.camera"},{"textInputSessions":[],"reportApplicationIdentifier":"FCFB2CD2-E55C-41EA-B9E1-C90BD6D17E60","usageTime":1,"bundleIdentifier":"com.apple.camera"},{"textInputSessions":[],"reportApplicationIdentifier":"CF9DAA9A-0604-43EC-B060-0706FF621974","usageTime":13,"bundleIdentifier":null},{"textInputSessions":[],"reportApplicationIdentifier":"CF9DAA9A-0604-43EC-B060-0706FF621974","usageTime":2,"bundleIdentifier":null},{"textInputSessions":[],"reportApplicationIdentifier":"5EB7400C-3B40-4720-8CDA-A0CA89EAB258","usageTime":82,"bundleIdentifier":null},{"textInputSessions":[],"reportApplicationIdentifier":"5EB7400C-3B40-4720-8CDA-A0CA89EAB258","usageTime":1,"bundleIdentifier":null},{"textInputSessions":[],"reportApplicationIdentifier":"CF9DAA9A-0604-43EC-B060-0706FF621974","usageTime":25,"bundleIdentifier":null},{"textInputSessions":[],"reportApplicationIdentifier":"CF9DAA9A-0604-43EC-B060-0706FF621974","usageTime":43,"bundleIdentifier":null}],"SRDeviceUsageCategoryProductivity",[{"textInputSessions":[{"duration":1.5045610666275024,"sessionType":"Keyboard"}],"reportApplicationIdentifier":"9137332D-E562-48CD-A907-2D91187B7161","usageTime":1,"bundleIdentifier":"com.apple.MobileSMS"},{"textInputSessions":[{"duration":1.5045610666275024,"sessionType":"Keyboard"}],"reportApplicationIdentifier":"9137332D-E562-48CD-A907-2D91187B7161","usageTime":4,"bundleIdentifier":"com.apple.MobileSMS"},{"textInputSessions":[{"duration":1.5045610666275024,"sessionType":"Keyboard"}],"reportApplicationIdentifier":"9137332D-E562-48CD-A907-2D91187B7161","usageTime":0,"bundleIdentifier":"com.apple.MobileSMS"}]],"duration":900,"totalUnlockDuration":683,"totalUnlocks":6,"notificationUsageByCategory":[]},"timestamp":"2022-09-28T20:29:59-0400"}]}